[
  {
    "name": "Teksupport: Mau P, Loco Dice, Discip",
    "venue": "Brooklyn Storehouse",
    "location": "Brooklyn, NY",
    "date": "2025-09-12"
  },
  {
    "name": "Two Friends, Ian Asher, Kaleena Zanders",
    "venue": "Central Park SummerStage",
    "location": "New York, NY",
    "date": "2025-09-12"
  },
  {
    "name": "Coone, Shogun",
    "venue": "The Meadows Brooklyn",
    "location": "Brooklyn, NY",
    "date": "2025-09-12"
  },
  {
    "name": "Marquee Skydeck: Two Friends",
    "venue": "Edge at Hudson Yards",
    "location": "New York, NY",
    "date": "2025-09-12"
  },
  {
    "name": "Swedish House Mafia",
    "venue": "Under the K Bridge Park",
    "location": "Brooklyn, NY",
    "date": "2025-09-12"
  },
  {
    "name": "Flosstradamus b2b 4B, TWONSKi",
    "venue": "Webster Hall",
    "location": "New York, NY",
    "date": "2025-09-12"
  },
  {
    "name": "Nebula Saturdays Events Sounds: ALEOS, Bassjackers",
    "venue": "Nebula",
    "location": "New York, NY",
    "date": "2025-09-12"
  },
  {
    "name": "Indo Warehouse: Kahani, Kunal Merchant, Anvaya, Anyasa, Firungi",
    "venue": "Brooklyn Paramount",
    "location": "Brooklyn, NY",
    "date": "2025-09-12"
  },
  {
    "name": "Big Wild, Shallou",
    "venue": "Brooklyn Bowl",
    "location": "Brooklyn, NY",
    "date": "2025-09-12"
  },
  {
    "name": "Vulfpeck",
    "venue": "Madison Square Garden",
    "location": "New York, NY",
    "date": "2025-09-13"
  },
  {
    "name": "Open To Close Set",
    "venue": "Brooklyn Storehouse",
    "location": "Brooklyn, NY",
    "date": "2025-09-13"
  },
  {
    "name": "TWO LANES, Robert Koch",
    "venue": "Brooklyn Steel",
    "location": "Brooklyn, NY",
    "date": "2025-09-13"
  },
  {
    "name": "demotapes, Eyezic, Nebita",
    "venue": "Elsewhere Zone One",
    "location": "Brooklyn, NY",
    "date": "2025-09-13"
  },
  {
    "name": "Through My System Tour: it's murph, Starjunk 95, Arlo",
    "venue": "Great Hall at Avant Gardner",
    "location": "Brooklyn, NY",
    "date": "2025-09-13"
  },
  {
    "name": "Marquee Skydeck: Lee Burridge",
    "venue": "Edge at Hudson Yards",
    "location": "New York, NY",
    "date": "2025-09-13"
  },
  {
    "name": "The Factory X Listen: Saeed Younan, Andy Cardona",
    "venue": "198 Randolph Street",
    "location": "Brooklyn, NY",
    "date": "2025-09-13"
  },
  {
    "name": "Gray Area Presents: Deep Dish, Dubfire, Sharam, Luna Mar, Khen, NURAN",
    "venue": "Superior Ingredients (Rooftop)",
    "location": "Brooklyn, NY",
    "date": "2025-09-14"
  },
  {
    "name": "James Hype",
    "venue": "The Summer Club",
    "location": "New York, NY",
    "date": "2025-09-14"
  },
  {
    "name": "Uncle Waffles, DJ AK, Chase B",
    "venue": "Rooftop at Pier 17",
    "location": "New York, NY",
    "date": "2025-09-14"
  },
  {
    "name": "Sol at 1 Hotel",
    "venue": "1 Hotel Brooklyn Bridge",
    "location": "Brooklyn, NY",
    "date": "2025-09-14"
  },
  {
    "name": "D.O.R Presents - Fashion Night Outside: Kush Jones, Daniro, BASSBEAR!!, Kai the Black Angel, Jay Envy",
    "venue": "SILO Brooklyn",
    "location": "Brooklyn, NY",
    "date": "2025-09-14"
  },
  {
    "name": "Cenote Project Open-Air Rooftop Sunset Party",
    "venue": "Somewhere Nowhere",
    "location": "New York, NY",
    "date": "2025-09-14"
  },
  {
    "name": "Eli Escobar, DJ Lloyd, Andy Pry",
    "venue": "Ruins at Knockdown Center",
    "location": "New York, NY",
    "date": "2025-09-14"
  },
  {
    "name": "Free RSVP",
    "venue": "Althea's Rooftop",
    "location": "New York, NY",
    "date": "2025-09-14"
  },
  {
    "name": "Ice Thompson",
    "venue": "Listen Brooklyn",
    "location": "Brooklyn, NY",
    "date": "2025-09-14"
  },
  {
    "name": "Sounday's Listen: Caroline Arnich, Tucci, A.S.A, J David",
    "venue": "Listen Brooklyn",
    "location": "Brooklyn, NY",
    "date": "2025-09-14"
  },
  {
    "name": "More Events \u2193",
    "venue": "TAO Downtown",
    "location": "New York, NY",
    "date": "2025-09-17"
  },
  {
    "name": "Polo & Pan, Tycho",
    "venue": "Brooklyn Storehouse",
    "location": "Brooklyn, NY",
    "date": "2025-09-18"
  },
  {
    "name": "The Chemical Brothers, Erol Alkan",
    "venue": "Knockdown Center",
    "location": "New York, NY",
    "date": "2025-09-18"
  },
  {
    "name": "BAYNK, Swoosh",
    "venue": "Elsewhere Rooftop",
    "location": "Brooklyn, NY",
    "date": "2025-09-18"
  },
  {
    "name": "Where Else Thursdays",
    "venue": "Somewhere Nowhere",
    "location": "New York, NY",
    "date": "2025-09-18"
  },
  {
    "name": "Pariah",
    "venue": "Signal Brooklyn",
    "location": "Brooklyn, NY",
    "date": "2025-09-18"
  },
  {
    "name": "Pariah",
    "venue": "The Fleur Room",
    "location": "New York, NY",
    "date": "2025-09-18"
  },
  {
    "name": "Tchami, AC Slater",
    "venue": "Nebula",
    "location": "New York, NY",
    "date": "2025-09-18"
  },
  {
    "name": "Palosanto on the Roof: Oktave, Temil",
    "venue": "The Roof at Arlo Williamsburg",
    "location": "Brooklyn, NY",
    "date": "2025-09-18"
  },
  {
    "name": "Groove Theory X Compass Rose Presents: A lana",
    "venue": "Moondog HiFi",
    "location": "Brooklyn, NY",
    "date": "2025-09-18"
  }
]