[
  {
    "name": "Neil Jackson",
    "venue": "TAO Downtown",
    "location": "New York, NY",
    "date": "2025-07-30"
  },
  {
    "name": "Village Hidden in Sound: Yedi, Eric Otero, Barris Fishman, PAX FM",
    "venue": "Jupiter Disco",
    "location": "Brooklyn, NY",
    "date": "2025-07-30"
  },
  {
    "name": "Subtronics, Boogie T, Smoakland, Zen Selekta, STVSH, INZO, Tripp St., A Hundred Drums, Gunpoint",
    "venue": "Great Hall at Avant Gardner",
    "location": "Brooklyn, NY",
    "date": "2025-07-31"
  },
  {
    "name": "DJ Neat Freak (Andrew VanWyngarden of MGMT)",
    "venue": "Public Records",
    "location": "Brooklyn, NY",
    "date": "2025-07-31"
  },
  {
    "name": "Summer Dayes: The Yussef Dayes Experience, FKJ, Venna, Salin",
    "venue": "Rumsey Playfield at Central Park",
    "location": "New York, NY",
    "date": "2025-07-31"
  },
  {
    "name": "St. Lucia",
    "venue": "Elsewhere Rooftop",
    "location": "Brooklyn, NY",
    "date": "2025-07-31"
  },
  {
    "name": "The Ornate Project: Chus, Benny Soto, Mike Nervous",
    "venue": "Harriet's Rooftop Brooklyn",
    "location": "Brooklyn, NY",
    "date": "2025-07-31"
  },
  {
    "name": "MEMBA",
    "venue": "1 Hotel Brooklyn Bridge",
    "location": "Brooklyn, NY",
    "date": "2025-07-31"
  },
  {
    "name": "EVENING TEA: Marco Weibel",
    "venue": "Silence Please",
    "location": "New York, NY",
    "date": "2025-07-31"
  },
  {
    "name": "Listening Session: Vicki Huang",
    "venue": "Silence Please",
    "location": "New York, NY",
    "date": "2025-07-31"
  },
  {
    "name": "Solace Ny: Ketzaal",
    "venue": "Earthly Delights",
    "location": "New York, NY",
    "date": "2025-07-31"
  },
  {
    "name": "AGAP\u0112 x SIGNAL: Saint Velez, Diossa, Junkfile, Adrian Hex, Ramsey Neville, evelyn",
    "venue": "Signal Brooklyn",
    "location": "Brooklyn, NY",
    "date": "2025-07-31"
  },
  {
    "name": "Jamie xx, Daphni, Carista, EVILGIANE, Pageant Queens",
    "venue": "Under the K Bridge Park",
    "location": "Brooklyn, NY",
    "date": "2025-08-01"
  },
  {
    "name": "Subtronics, INZO, Tripp St., A Hundred Drums, Gunpoint",
    "venue": "Great Hall at Avant Gardner",
    "location": "Brooklyn, NY",
    "date": "2025-08-01"
  },
  {
    "name": "\u00d8TTA, Franck",
    "venue": "Elsewhere Rooftop",
    "location": "Brooklyn, NY",
    "date": "2025-08-01"
  },
  {
    "name": "Teksupport: Prospa",
    "venue": "Sunset Park Rooftop",
    "location": "Brooklyn, NY",
    "date": "2025-08-01"
  },
  {
    "name": "A-Trak, Moon Boots, Oliver $, SKY JETTA",
    "venue": "Elsewhere",
    "location": "Brooklyn, NY",
    "date": "2025-08-01"
  },
  {
    "name": "Shl\u00f8mo, hhunter, JSMN",
    "venue": "Superior Ingredients (Rooftop)",
    "location": "Brooklyn, NY",
    "date": "2025-08-01"
  },
  {
    "name": "Marquee Skydeck: Alan Walker",
    "venue": "Edge at Hudson Yards",
    "location": "New York, NY",
    "date": "2025-08-01"
  },
  {
    "name": "SKSKSKS+Boots: SoFTT, Bodysync, GRRL",
    "venue": "SILO Brooklyn",
    "location": "Brooklyn, NY",
    "date": "2025-08-01"
  },
  {
    "name": "Lukas Wigflex, Maksim, Joiah, Daniel Dutts",
    "venue": "Signal Brooklyn",
    "location": "Brooklyn, NY",
    "date": "2025-08-01"
  },
  {
    "name": "Turbz",
    "venue": "Little Sister Lounge",
    "location": "New York, NY",
    "date": "2025-08-01"
  },
  {
    "name": "Jamie xx, Carl Craig, Marie Davidson, Carlos Souffront, SEES00000, Anysia Kym",
    "venue": "Under the K Bridge Park",
    "location": "Brooklyn, NY",
    "date": "2025-08-02"
  },
  {
    "name": "Teksupport: Patrick Topping",
    "venue": "Sunset Park Rooftop",
    "location": "Brooklyn, NY",
    "date": "2025-08-02"
  },
  {
    "name": "Space Laces, Nitepunk, Zubah",
    "venue": "Webster Hall",
    "location": "New York, NY",
    "date": "2025-08-02"
  },
  {
    "name": "Teksupport: Ben Sterling",
    "venue": "99 Scott Ave",
    "location": "Brooklyn, NY",
    "date": "2025-08-02"
  },
  {
    "name": "Support Women DJs x Bass n Babes Present: Austeria, LYSN., Baby Kush, Lex Looper",
    "venue": "The Meadows Brooklyn",
    "location": "Brooklyn, NY",
    "date": "2025-08-02"
  },
  {
    "name": "Com Truise",
    "venue": "SILO Brooklyn",
    "location": "Brooklyn, NY",
    "date": "2025-08-02"
  },
  {
    "name": "Teksupport at Sea: Nicole Moudaber",
    "venue": "Pier 81 (NYC)",
    "location": "New York, NY",
    "date": "2025-08-02"
  },
  {
    "name": "The Disco Fries, Tommie Sunshine",
    "venue": "Brooklyn Bowl",
    "location": "Brooklyn, NY",
    "date": "2025-08-02"
  },
  {
    "name": "All Day I Dream of Summer Shimmer: Lee Burridge, Tim Green, Facundo Mohrr, Newman (I Love), Tommy Raffa",
    "venue": "Industry City Courtyard 1/2",
    "location": "Brooklyn, NY",
    "date": "2025-08-03"
  },
  {
    "name": "The Summer Club Presents: Martin Ikin",
    "venue": "The Summer Club",
    "location": "New York, NY",
    "date": "2025-08-03"
  },
  {
    "name": "BIG DRUM & BASS PARTY: Dieselboy, DrivenAM (Agent 137 & David Shichman), Ben Soundscape, B33, Gabriel Habit",
    "venue": "Sultan Room Rooftop",
    "location": "Brooklyn, NY",
    "date": "2025-08-03"
  },
  {
    "name": "Gray Area Presents: Eli & Fur",
    "venue": "Superior Ingredients (Rooftop)",
    "location": "Brooklyn, NY",
    "date": "2025-08-03"
  },
  {
    "name": "DJ Sprinkles, Frank & Tony",
    "venue": "The Nursery at Public Records",
    "location": "Brooklyn, NY",
    "date": "2025-08-03"
  },
  {
    "name": "Presented by Forest D\u00f6wn Under: Lohrasp Kansara, Siwell, CHASKE",
    "venue": "Somewhere Nowhere",
    "location": "New York, NY",
    "date": "2025-08-03"
  },
  {
    "name": "South House Presents - Sunday Service x Social Club Atlanta",
    "venue": "53 Scott Ave",
    "location": "Brooklyn, NY",
    "date": "2025-08-03"
  },
  {
    "name": "FriendZone Back To The Light House: Kenny Glasgow",
    "venue": "Light House",
    "location": "Brooklyn, NY",
    "date": "2025-08-03"
  },
  {
    "name": "Mamba Mondays",
    "venue": "Althea's Hideaway",
    "location": "New York, NY",
    "date": "2025-08-04"
  },
  {
    "name": "Misuser",
    "venue": "Berlin Under A",
    "location": "New York, NY",
    "date": "2025-08-04"
  },
  {
    "name": "Francis Mercier",
    "venue": "Industry City",
    "location": "Brooklyn, NY",
    "date": "2025-07-29"
  },
  {
    "name": "Gray Area Presents: Justin Martin, Eskuche, Cristina Lazic, Cut & Sew",
    "venue": "Superior Ingredients (Rooftop)",
    "location": "Brooklyn, NY",
    "date": "2025-07-29"
  },
  {
    "name": "Sunset Reverie",
    "venue": "Public Hotel Rooftop",
    "location": "New York, NY",
    "date": "2025-07-29"
  },
  {
    "name": "Paurro, Korn\u00e9l Kov\u00e1cs",
    "venue": "The Nursery at Public Records",
    "location": "Brooklyn, NY",
    "date": "2025-07-29"
  },
  {
    "name": "A lana, IRL, Subcultures",
    "venue": "Jupiter Disco",
    "location": "Brooklyn, NY",
    "date": "2025-07-29"
  },
  {
    "name": "Resurrection - Dominican Night: Maya Margarita, Dada Cozmic, Fried Pl\u00e1tano, Br0nz3_G0dd3ss, Sterling Juan Diaz, Alexis De La Rosa, Jeremy Giros, Bendito, Donis, Total XTC, Honey Dip",
    "venue": "Paragon",
    "location": "Brooklyn, NY",
    "date": "2025-07-29"
  },
  {
    "name": "Aspirin, Grant Tyler, Jaesyun, sooZ",
    "venue": "AURA 57 NYC",
    "location": "New York, NY",
    "date": "2025-07-29"
  },
  {
    "name": "Eamon Harkin, Justin Carter",
    "venue": "Nowadays",
    "location": "New York, NY",
    "date": "2025-07-29"
  },
  {
    "name": "**LIMITED FREE RSVP**",
    "venue": "Spring Place",
    "location": "New York, NY",
    "date": "2025-07-29"
  },
  {
    "name": "Bloodsport (SAYMYNAME & Riot Ten)",
    "venue": "Parklife",
    "location": "Brooklyn, NY",
    "date": "2025-07-29"
  },
  {
    "name": "Alesso",
    "venue": "Brooklyn Mirage",
    "location": "Brooklyn, NY",
    "date": "2025-07-29"
  },
  {
    "name": "Mojave Grey",
    "venue": "Elsewhere Rooftop",
    "location": "Brooklyn, NY",
    "date": "2025-07-29"
  },
  {
    "name": "Amelia Holt, Second Contact, Magda, Planet B",
    "venue": "Nowadays",
    "location": "New York, NY",
    "date": "2025-07-29"
  },
  {
    "name": "Neil Jackson",
    "venue": "The Fleur Room",
    "location": "New York, NY",
    "date": "2025-07-29"
  },
  {
    "name": "pregame: Cristi Cons, Armii1n, Choukroun, Per Hammar",
    "venue": "Signal Brooklyn",
    "location": "Brooklyn, NY",
    "date": "2025-07-29"
  },
  {
    "name": "Lounge Sessions: Anthony Romano, Josie., LEFTI",
    "venue": "SILO Brooklyn",
    "location": "Brooklyn, NY",
    "date": "2025-07-29"
  },
  {
    "name": "Gray Area Presents: J. Worra, Benson, Jenn Getz & Alfie, Eve Lauren",
    "venue": "Ruins at Knockdown Center",
    "location": "New York, NY",
    "date": "2025-08-01"
  },
  {
    "name": "Nala, Fundido, Lee Cash",
    "venue": "Elsewhere Rooftop",
    "location": "Brooklyn, NY",
    "date": "2025-08-01"
  },
  {
    "name": "Nicola Cruz, 98dots, mach\u00ecna",
    "venue": "Knockdown Center",
    "location": "New York, NY",
    "date": "2025-08-01"
  },
  {
    "name": "STORIES Open Air by Gray Are: Sarah Story",
    "venue": "H0L0 Yard",
    "location": "New York, NY",
    "date": "2025-08-01"
  },
  {
    "name": "Jovonn, D'Sean, Greg Caz",
    "venue": "Dead Letter No. 9",
    "location": "Brooklyn, NY",
    "date": "2025-08-01"
  },
  {
    "name": "Dillon Nathaniel, NightFunk",
    "venue": "SILO Brooklyn",
    "location": "Brooklyn, NY",
    "date": "2025-08-01"
  },
  {
    "name": "Mike Nasty, Checko Spinz",
    "venue": "Cafe Erzulie",
    "location": "Brooklyn, NY",
    "date": "2025-08-01"
  },
  {
    "name": "RSVP",
    "venue": "00:00",
    "location": "New York, NY",
    "date": "2025-08-01"
  },
  {
    "name": "Gene Farris",
    "venue": "Listen Brooklyn",
    "location": "Brooklyn, NY",
    "date": "2025-08-01"
  },
  {
    "name": "Teksupport: Max Dean, B Luke, Luke Dean",
    "venue": "Sunset Park Rooftop",
    "location": "Brooklyn, NY",
    "date": "2025-07-29"
  },
  {
    "name": "Gray Area presents grayscale: Juliet Fox, Caravel",
    "venue": "Brooklyn Monarch",
    "location": "Brooklyn, NY",
    "date": "2025-07-29"
  },
  {
    "name": "Laidback Luke",
    "venue": "Nebula",
    "location": "New York, NY",
    "date": "2025-07-29"
  },
  {
    "name": "Themba",
    "venue": "Great Hall at Avant Gardner",
    "location": "Brooklyn, NY",
    "date": "2025-07-29"
  },
  {
    "name": "VRG, Hexxa, BLUPILL",
    "venue": "The Woodshop Brooklyn",
    "location": "Brooklyn, NY",
    "date": "2025-07-29"
  },
  {
    "name": "Flight Facilities, Blu DeTiger, Jasper Tygner, Fundido",
    "venue": "Knockdown Center",
    "location": "New York, NY",
    "date": "2025-07-29"
  },
  {
    "name": "Midnight Caviar: Jake the Rapper, Sleepy & Boo, \u1eccba+Flip",
    "venue": "Signal Brooklyn",
    "location": "Brooklyn, NY",
    "date": "2025-07-29"
  },
  {
    "name": "Maccabi House: Adam Ten, Mita Gami, Saqib, Monobase",
    "venue": "Brooklyn (Outdoors)",
    "location": "Brooklyn, NY",
    "date": "2025-07-29"
  },
  {
    "name": "Leonce, Mike Servito, Ryan Smith, Clarisa Kimskii, Ron Like Hell",
    "venue": "BASEMENT NY",
    "location": "New York, NY",
    "date": "2025-07-29"
  },
  {
    "name": "San Holo",
    "venue": "The Summer Club",
    "location": "New York, NY",
    "date": "2025-07-29"
  },
  {
    "name": "718 Sessions: Danny Krivit, Gide\u00f6n",
    "venue": "Ruins at Knockdown Center",
    "location": "New York, NY",
    "date": "2025-07-29"
  },
  {
    "name": "Laxcity, gabby start, Nebita",
    "venue": "Elsewhere Zone One",
    "location": "Brooklyn, NY",
    "date": "2025-07-29"
  },
  {
    "name": "The Summer Club Presents: James Kennedy",
    "venue": "The Summer Club",
    "location": "New York, NY",
    "date": "2025-07-29"
  },
  {
    "name": "warner case",
    "venue": "Elsewhere Rooftop",
    "location": "Brooklyn, NY",
    "date": "2025-07-29"
  },
  {
    "name": "Gray Area Presents",
    "venue": "Superior Ingredients (Rooftop)",
    "location": "Brooklyn, NY",
    "date": "2025-07-29"
  },
  {
    "name": "Yarden Saxophone",
    "venue": "Public Hotel Rooftop",
    "location": "New York, NY",
    "date": "2025-07-29"
  },
  {
    "name": "Presented by Forest D\u00f6wn Under: Oscar G, Cristian Arango",
    "venue": "Somewhere Nowhere",
    "location": "New York, NY",
    "date": "2025-07-29"
  },
  {
    "name": "Sonja Moonear, AIDA",
    "venue": "The Nursery at Public Records",
    "location": "Brooklyn, NY",
    "date": "2025-07-29"
  },
  {
    "name": "Avalon Emerson, Eamon Harkin",
    "venue": "Nowadays",
    "location": "New York, NY",
    "date": "2025-07-29"
  },
  {
    "name": "Discovery Sessions: SLAMM, Miata Boys, JaySide, Gavin Gone",
    "venue": "SILO Brooklyn",
    "location": "Brooklyn, NY",
    "date": "2025-07-29"
  },
  {
    "name": "Cenote Project Open-Air Rooftop Sunset Party: Lohrasp Kansara, Watson, Mech",
    "venue": "Somewhere Nowhere",
    "location": "New York, NY",
    "date": "2025-07-29"
  },
  {
    "name": "NAACH X Sonance: Unders, Dramian, Nacho Isa, Fireware",
    "venue": "Arlo Williamsburg",
    "location": "Brooklyn, NY",
    "date": "2025-07-29"
  },
  {
    "name": "Synthony",
    "venue": "Brooklyn Mirage",
    "location": "Brooklyn, NY",
    "date": "2025-07-29"
  },
  {
    "name": "Jake Muir",
    "venue": "Public Records",
    "location": "Brooklyn, NY",
    "date": "2025-07-29"
  },
  {
    "name": "shadowofadoubt, Roselle, Nondough",
    "venue": "Jupiter Disco",
    "location": "Brooklyn, NY",
    "date": "2025-07-29"
  },
  {
    "name": "Mindchatter, Shek",
    "venue": "Public Records",
    "location": "Brooklyn, NY",
    "date": "2025-07-29"
  },
  {
    "name": "Planet Yes - Gasolina: DJ Ultra Violet",
    "venue": "House of Yes",
    "location": "Brooklyn, NY",
    "date": "2025-07-29"
  },
  {
    "name": "Laila Amira, Lady Harley",
    "venue": "Jupiter Disco",
    "location": "Brooklyn, NY",
    "date": "2025-07-29"
  },
  {
    "name": "Kiss Kiss",
    "venue": "C'mon Everybody",
    "location": "Brooklyn, NY",
    "date": "2025-07-29"
  },
  {
    "name": "Gray Area Presents: Wakyin",
    "venue": "Ruins at Knockdown Center",
    "location": "New York, NY",
    "date": "2025-07-29"
  },
  {
    "name": "Gray Area Presents: KREAM, Adam Sellouk",
    "venue": "Knockdown Center",
    "location": "New York, NY",
    "date": "2025-07-29"
  },
  {
    "name": "Nora En Pure, Jan Blomqvist, Paradoks",
    "venue": "Brooklyn Mirage",
    "location": "Brooklyn, NY",
    "date": "2025-07-29"
  },
  {
    "name": "Above(Ten): KC Lights",
    "venue": "1 Hotel Brooklyn Bridge",
    "location": "Brooklyn, NY",
    "date": "2025-07-29"
  },
  {
    "name": "Djibouti",
    "venue": "Elsewhere Rooftop",
    "location": "Brooklyn, NY",
    "date": "2025-07-29"
  },
  {
    "name": "Jantsen",
    "venue": "SILO Brooklyn",
    "location": "Brooklyn, NY",
    "date": "2025-07-29"
  },
  {
    "name": "Max Cooper",
    "venue": "Elsewhere Hall",
    "location": "Brooklyn, NY",
    "date": "2025-07-29"
  },
  {
    "name": "Lost Miracle presents: S\u00e9bastien L\u00e9ger, Roy Rosenfeld",
    "venue": "Superior Ingredients (Rooftop)",
    "location": "Brooklyn, NY",
    "date": "2025-07-29"
  },
  {
    "name": "Know Good",
    "venue": "Bowery Ballroom",
    "location": "New York, NY",
    "date": "2025-07-29"
  },
  {
    "name": "Julia Govor, Sister Zo, nataliepops",
    "venue": "House of Yes",
    "location": "Brooklyn, NY",
    "date": "2025-07-29"
  },
  {
    "name": "EMBRZ",
    "venue": "Spring Place",
    "location": "New York, NY",
    "date": "2025-08-02"
  },
  {
    "name": "Darude",
    "venue": "Webster Hall",
    "location": "New York, NY",
    "date": "2025-08-02"
  },
  {
    "name": "Timmy Trumpet, Yellow Claw, Ely Oaks, Sunday Scaries",
    "venue": "Great Hall at Avant Gardner",
    "location": "Brooklyn, NY",
    "date": "2025-08-02"
  },
  {
    "name": "Blastoyz Back in Brooklyn: Chriscendo",
    "venue": "The Meadows Brooklyn",
    "location": "Brooklyn, NY",
    "date": "2025-08-02"
  },
  {
    "name": "Me Me Me Me - A Leo Party: DJ Haram, Boyyyish, SilkyBlack",
    "venue": "House of Yes",
    "location": "Brooklyn, NY",
    "date": "2025-08-02"
  },
  {
    "name": "Unveiled Presents: Calussa",
    "venue": "UNVEILED",
    "location": "Brooklyn, NY",
    "date": "2025-08-02"
  },
  {
    "name": "Yum! - A Drum And Bass Rave!: Georgie Riot, Jaesyun, Ultra dnb, DAve Schichman, Yetti, E-Mood, Alex English (DJ), Rayn, Nito, Pachelle, Remniqe, Chemistry MC, AERO MC, Hambone, Last Action Heroes, SUPR SPRT",
    "venue": "The Meadows Brooklyn",
    "location": "Brooklyn, NY",
    "date": "2025-08-02"
  },
  {
    "name": "Loud Luxury",
    "venue": "The Summer Club",
    "location": "New York, NY",
    "date": "2025-08-02"
  },
  {
    "name": "Theo Parrish",
    "venue": "Industry City",
    "location": "Brooklyn, NY",
    "date": "2025-08-02"
  },
  {
    "name": "Zeds Dead",
    "venue": "Brooklyn Bowl",
    "location": "Brooklyn, NY",
    "date": "2025-08-02"
  },
  {
    "name": "Black Coffee",
    "venue": "Brooklyn Mirage",
    "location": "Brooklyn, NY",
    "date": "2025-07-29"
  },
  {
    "name": "We Are Eclipse: Lauren Ritter, Camila Wolf, Jean Paul, JLU, REVA",
    "venue": "Elsewhere Rooftop",
    "location": "Brooklyn, NY",
    "date": "2025-07-29"
  },
  {
    "name": "Gray Area Presents: America Rose, bad tuner, Gilligan Moss, Phantoms",
    "venue": "Superior Ingredients (Rooftop)",
    "location": "Brooklyn, NY",
    "date": "2025-07-29"
  },
  {
    "name": "Josh Butler",
    "venue": "Spring Place",
    "location": "New York, NY",
    "date": "2025-07-29"
  },
  {
    "name": "San Pacho",
    "venue": "The Summer Club",
    "location": "New York, NY",
    "date": "2025-07-29"
  },
  {
    "name": "Burning Bush Yacht Party: It's Just Joe",
    "venue": "Skyport Marina",
    "location": "New York, NY",
    "date": "2025-07-29"
  },
  {
    "name": "Eamon Harkin, Leeon",
    "venue": "Nowadays",
    "location": "New York, NY",
    "date": "2025-07-29"
  },
  {
    "name": "RUMBLE - 4 The Dancers",
    "venue": "Jupiter Disco",
    "location": "Brooklyn, NY",
    "date": "2025-07-29"
  },
  {
    "name": "Wooli, Zingara, Automhate b2b MAD DUBZ, Fairlane, Capochino",
    "venue": "Brooklyn Mirage",
    "location": "Brooklyn, NY",
    "date": "2025-07-29"
  },
  {
    "name": "Photek",
    "venue": "Public Records",
    "location": "Brooklyn, NY",
    "date": "2025-07-29"
  },
  {
    "name": "HIGH-SEAS",
    "venue": "Earthly Delights",
    "location": "New York, NY",
    "date": "2025-07-29"
  },
  {
    "name": "Boris Werner, Ben Balance, Joiah",
    "venue": "Signal Brooklyn",
    "location": "Brooklyn, NY",
    "date": "2025-07-29"
  },
  {
    "name": "Beltran, Avision, CatLadyHi, Special Guest",
    "venue": "Sunset Park Rooftop",
    "location": "Brooklyn, NY",
    "date": "2025-07-29"
  },
  {
    "name": "A. G. Cook, Rick Farin",
    "venue": "Brooklyn Paramount",
    "location": "Brooklyn, NY",
    "date": "2025-07-29"
  },
  {
    "name": "Drumcode NYC: Adam Beyer, Bart Skils, Victor Ruiz, Charles D, HNTR, Kasia, Konstantin Sibold",
    "venue": "Great Hall at Avant Gardner",
    "location": "Brooklyn, NY",
    "date": "2025-07-29"
  },
  {
    "name": "Bad Boombox, Mija, Mischluft, Ollie Lishman",
    "venue": "Knockdown Center",
    "location": "New York, NY",
    "date": "2025-07-29"
  },
  {
    "name": "Stacey Pullen, Harry Romero, Mat.Joe, Street Slang",
    "venue": "Palladium Times Square",
    "location": "New York, NY",
    "date": "2025-07-29"
  },
  {
    "name": "Morgan Page",
    "venue": "SILO Brooklyn",
    "location": "Brooklyn, NY",
    "date": "2025-07-29"
  },
  {
    "name": "Beltran, ChaseWest, Obsk\u00fcr, Pablo Romero",
    "venue": "99 Scott Ave",
    "location": "Brooklyn, NY",
    "date": "2025-07-29"
  },
  {
    "name": "rAwR xD: Breaka, BRUX, ZOF",
    "venue": "House of Yes",
    "location": "Brooklyn, NY",
    "date": "2025-07-29"
  },
  {
    "name": "VKTM, XaeboR, TWOPERCENT",
    "venue": "The Meadows Brooklyn",
    "location": "Brooklyn, NY",
    "date": "2025-07-29"
  },
  {
    "name": "Valentino Khan",
    "venue": "Mission Nightclub",
    "location": "New York, NY",
    "date": "2025-07-29"
  },
  {
    "name": "Swami Sound, gum.mp3",
    "venue": "Market Hotel",
    "location": "Brooklyn, NY",
    "date": "2025-07-29"
  },
  {
    "name": "Anja Schneider, Musumeci",
    "venue": "Signal Brooklyn",
    "location": "Brooklyn, NY",
    "date": "2025-07-29"
  },
  {
    "name": "Yung Singh",
    "venue": "Superior Ingredients (Rooftop)",
    "location": "Brooklyn, NY",
    "date": "2025-07-29"
  },
  {
    "name": "Hot Since 82, Prunk, Mai Iachetti, Le Yora, Colored Craig",
    "venue": "Knockdown Center",
    "location": "New York, NY",
    "date": "2025-07-29"
  },
  {
    "name": "Marquee Skydeck: Benny Benassi",
    "venue": "Edge at Hudson Yards",
    "location": "New York, NY",
    "date": "2025-07-29"
  },
  {
    "name": "Justin Strauss, Honey B, Donis, VARSHA, Sevyn, Darone Sassounian",
    "venue": "Public Records",
    "location": "Brooklyn, NY",
    "date": "2025-07-29"
  },
  {
    "name": "Eptic",
    "venue": "Le Poisson Rouge",
    "location": "New York, NY",
    "date": "2025-07-29"
  },
  {
    "name": "Project 91: Two Friends",
    "venue": "The Summer Club",
    "location": "New York, NY",
    "date": "2025-07-29"
  },
  {
    "name": "BK Loves UKG: Boombox Cartel, Great Dane, Kenzii Scott, Samisosa",
    "venue": "Elsewhere",
    "location": "Brooklyn, NY",
    "date": "2025-07-29"
  },
  {
    "name": "Presented by Forest D\u00f6wn Under: Shortkutz, Luchini",
    "venue": "Somewhere Nowhere",
    "location": "New York, NY",
    "date": "2025-07-29"
  },
  {
    "name": "DJ Snake",
    "venue": "Brooklyn Mirage",
    "location": "Brooklyn, NY",
    "date": "2025-08-03"
  },
  {
    "name": "Jerro",
    "venue": "Spring Place",
    "location": "New York, NY",
    "date": "2025-08-03"
  },
  {
    "name": "Moojo",
    "venue": "Somewhere Nowhere",
    "location": "New York, NY",
    "date": "2025-08-03"
  },
  {
    "name": "Gray Area Presents: Luttrell",
    "venue": "Superior Ingredients (Rooftop)",
    "location": "Brooklyn, NY",
    "date": "2025-08-03"
  },
  {
    "name": "Cloonee",
    "venue": "The Summer Club",
    "location": "New York, NY",
    "date": "2025-08-03"
  },
  {
    "name": "Dimension",
    "venue": "Great Hall at Avant Gardner",
    "location": "Brooklyn, NY",
    "date": "2025-08-03"
  },
  {
    "name": "Kaskade",
    "venue": "Under the K Bridge Park (19 Bridgewater Street)",
    "location": "Brooklyn, NY",
    "date": "2025-08-03"
  },
  {
    "name": "Horse Meat Disco, Luke Solomon",
    "venue": "Knockdown Center",
    "location": "New York, NY",
    "date": "2025-08-03"
  },
  {
    "name": "Azure Day Party: Luke Alexander, Mikey Barreneche",
    "venue": "Arlo Williamsburg",
    "location": "Brooklyn, NY",
    "date": "2025-08-03"
  }
]