[
  {
    "name": "Chizzle",
    "venue": "Marquee",
    "location": "New York, NY",
    "date": "2026-02-25"
  },
  {
    "name": "AceMo, Christian Tokyo",
    "venue": "Club 101 NYC",
    "location": "New York, NY",
    "date": "2026-02-25"
  },
  {
    "name": "Red Axes",
    "venue": "Public Records",
    "location": "Brooklyn, NY",
    "date": "2026-02-26"
  },
  {
    "name": "Fraxiom, gupi",
    "venue": "Elsewhere Hall",
    "location": "Brooklyn, NY",
    "date": "2026-02-26"
  },
  {
    "name": "Vigilante Presents: Hovy, Lauren Ritter, Adam Collins",
    "venue": "Outer Heaven NYC",
    "location": "New York, NY",
    "date": "2026-02-26"
  },
  {
    "name": "Jay Prouty",
    "venue": "Moondog HiFi",
    "location": "Brooklyn, NY",
    "date": "2026-02-26"
  },
  {
    "name": "DJ Travella, Gatorface, Anysia Kym, Possum",
    "venue": "Paragon",
    "location": "Brooklyn, NY",
    "date": "2026-02-26"
  },
  {
    "name": "Thursdays are Casual: Vesi, Tempo Twist",
    "venue": "Virgo New York",
    "location": "New York, NY",
    "date": "2026-02-26"
  },
  {
    "name": "Trip Don't Sleep: Auphoria, Armii1n, Choukroun, Brunno Lima",
    "venue": "MAD Radio NYC",
    "location": "Brooklyn, NY",
    "date": "2026-02-26"
  },
  {
    "name": "Benjamin Lloyd",
    "venue": "Marquee",
    "location": "New York, NY",
    "date": "2026-02-27"
  },
  {
    "name": "Fibonacci Tour: Subtronics, Yetti, TroyBoi, capshun, AVELLO, Juelz, Roots, Blossom",
    "venue": "Brooklyn Storehouse",
    "location": "Brooklyn, NY",
    "date": "2026-02-27"
  },
  {
    "name": "camoufly, MATRAKK",
    "venue": "Elsewhere",
    "location": "Brooklyn, NY",
    "date": "2026-02-27"
  },
  {
    "name": "RUSH Presents: KI/KI, Lauren Flax, LYDO",
    "venue": "Knockdown Center",
    "location": "New York, NY",
    "date": "2026-02-27"
  },
  {
    "name": "Timecop1983, The Bad Dreamers",
    "venue": "Music Hall of Williamsburg",
    "location": "Brooklyn, NY",
    "date": "2026-02-27"
  },
  {
    "name": "Danny L Harle",
    "venue": "Elsewhere Hall",
    "location": "Brooklyn, NY",
    "date": "2026-02-27"
  },
  {
    "name": "Eli Escobar, Cosmo",
    "venue": "Signal Brooklyn",
    "location": "Brooklyn, NY",
    "date": "2026-02-27"
  },
  {
    "name": "Kamino",
    "venue": "Nebula",
    "location": "New York, NY",
    "date": "2026-02-27"
  },
  {
    "name": "Club Stars: DJ Assault, Raven, Daniro, Swan Meat, WTCHCRFT",
    "venue": "Paragon",
    "location": "Brooklyn, NY",
    "date": "2026-02-27"
  },
  {
    "name": "Tom & Collins, Sam Allan",
    "venue": "1 Hotel Brooklyn Bridge",
    "location": "Brooklyn, NY",
    "date": "2026-02-28"
  },
  {
    "name": "Martin Ikin",
    "venue": "The Summer Club",
    "location": "New York, NY",
    "date": "2026-02-28"
  },
  {
    "name": "INZO, Know Good, Super Future, Blookah, Lhasa Petik",
    "venue": "Brooklyn Steel",
    "location": "Brooklyn, NY",
    "date": "2026-02-28"
  },
  {
    "name": "Peaches, Model/Actriz",
    "venue": "Knockdown Center",
    "location": "New York, NY",
    "date": "2026-02-28"
  },
  {
    "name": "Fibonacci Tour: Subtronics, Yetti, TroyBoi, capshun",
    "venue": "Brooklyn Storehouse",
    "location": "Brooklyn, NY",
    "date": "2026-02-28"
  },
  {
    "name": "HNTR, Rafael Cerato, Kenzii Scott, Marta",
    "venue": "99 Scott",
    "location": "Brooklyn, NY",
    "date": "2026-02-28"
  },
  {
    "name": "Son of Son, Henri Bergmann, Ka\u00ef, Fireware",
    "venue": "Superior Ingredients (Rooftop)",
    "location": "Brooklyn, NY",
    "date": "2026-02-28"
  },
  {
    "name": "Richie Hawtin, DJ Stingray 313, Lindsey Herbert",
    "venue": "Knockdown Center",
    "location": "New York, NY",
    "date": "2026-02-28"
  },
  {
    "name": "Flava D, Ultra, Render One, DJ Nope, LeCamille, AERO MC, Jonas Loeb",
    "venue": "The Wood Shop",
    "location": "Brooklyn, NY",
    "date": "2026-02-28"
  },
  {
    "name": "Jackie Hollander",
    "venue": "Superior Ingredients",
    "location": "Brooklyn, NY",
    "date": "2026-03-01"
  },
  {
    "name": "Amelia Holt, Bouffant Bouffant, Kilopatrah Jones, Second Contact",
    "venue": "Public Records",
    "location": "Brooklyn, NY",
    "date": "2026-03-01"
  },
  {
    "name": "B444dlove",
    "venue": "20 Meadow Street",
    "location": "Brooklyn, NY",
    "date": "2026-03-01"
  },
  {
    "name": "Gaspar Muniz",
    "venue": "House of Yes",
    "location": "Brooklyn, NY",
    "date": "2026-03-01"
  },
  {
    "name": "Loco Carnaval Sundays: Lohrasp Kansara, Cyrus X, Rowan, Mayte",
    "venue": "Somewhere Nowhere",
    "location": "New York, NY",
    "date": "2026-03-01"
  },
  {
    "name": "Sunday Selectors: Kim Lightfoot",
    "venue": "Refuge",
    "location": "Brooklyn, NY",
    "date": "2026-03-01"
  },
  {
    "name": "Vin Sol, Lovie, Aaron Clark, Clark Price, d'Adhemar",
    "venue": "Signal Brooklyn",
    "location": "Brooklyn, NY",
    "date": "2026-03-01"
  },
  {
    "name": "Golden Record Presents: tINI, BEIGE",
    "venue": "East Williamsburg",
    "location": "Brooklyn, NY",
    "date": "2026-03-01"
  },
  {
    "name": "Sunday Skate Club: Sinkane, Bazaar Disco, W. Andrew Raposo, Skater_Tee",
    "venue": "Xanadu Roller Arts",
    "location": "Brooklyn, NY",
    "date": "2026-03-01"
  },
  {
    "name": "Selector Cycle - Deep Listening",
    "venue": "Moondog HiFi",
    "location": "Brooklyn, NY",
    "date": "2026-03-01"
  },
  {
    "name": "KUFF",
    "venue": "96 Morgan Ave",
    "location": "Brooklyn, NY",
    "date": "2026-03-01"
  },
  {
    "name": "Purim Madness: Matt Dubb, Levyticus",
    "venue": "Marquee",
    "location": "New York, NY",
    "date": "2026-03-02"
  },
  {
    "name": "Magda, S\u016bn Byrd, Star's Revenge, activemirror., FAT CONCUBINE, Bad Tomato, borscht",
    "venue": "Pianos",
    "location": "New York, NY",
    "date": "2026-03-03"
  },
  {
    "name": "Magit Cacoon",
    "venue": "Eden NYC",
    "location": "New York, NY",
    "date": "2026-03-03"
  },
  {
    "name": "Jus-Ske",
    "venue": "Little Sister Lounge",
    "location": "New York, NY",
    "date": "2026-03-03"
  },
  {
    "name": "Saxsquatch, Electric Dad, Light Chaser",
    "venue": "Racket New York",
    "location": "New York, NY",
    "date": "2026-02-25"
  },
  {
    "name": "Saxsquatch, Electric Dad, Light Chaser",
    "venue": "Little Sister Lounge",
    "location": "New York, NY",
    "date": "2026-02-25"
  },
  {
    "name": "Holding Pattern: Alex Compton, Ben Bondy, Goyle",
    "venue": "Trans-Pecos",
    "location": "New York, NY",
    "date": "2026-02-25"
  },
  {
    "name": "Names Divine \u2022 Spires That in the Sunset Rise: Lubelski",
    "venue": "Union Pool",
    "location": "Brooklyn, NY",
    "date": "2026-02-25"
  },
  {
    "name": "dh2 Label Night: George Daniel, Oscar Farrell, 2D0GS",
    "venue": "Public Records",
    "location": "Brooklyn, NY",
    "date": "2026-02-25"
  },
  {
    "name": "AFROJACK (Kapuchon Set)",
    "venue": "Refuge",
    "location": "Brooklyn, NY",
    "date": "2026-02-25"
  },
  {
    "name": "Soir\u00e9e Presents: Nicolas Matar, Krane b2b Camila W\u00f6lf, AMBA",
    "venue": "Signal Brooklyn",
    "location": "Brooklyn, NY",
    "date": "2026-02-25"
  },
  {
    "name": "Third Floor Sounds: Analog Soul, TEE EM DEE, DJ Shannon",
    "venue": "H0L0",
    "location": "New York, NY",
    "date": "2026-02-25"
  },
  {
    "name": "Turbz",
    "venue": "Little Sister Lounge",
    "location": "New York, NY",
    "date": "2026-02-25"
  },
  {
    "name": "Kimby",
    "venue": "Moondog HiFi",
    "location": "Brooklyn, NY",
    "date": "2026-02-25"
  },
  {
    "name": "AYYBO",
    "venue": "Knockdown Center",
    "location": "New York, NY",
    "date": "2026-02-25"
  },
  {
    "name": "Christian L\u00f6ffler, Otherwish",
    "venue": "Elsewhere Hall",
    "location": "Brooklyn, NY",
    "date": "2026-02-25"
  },
  {
    "name": "MUZZ, Dieselboy, Dave Shichman",
    "venue": "Car Park",
    "location": "Brooklyn, NY",
    "date": "2026-02-25"
  },
  {
    "name": "Nikita the Wicked",
    "venue": "Elsewhere Zone One",
    "location": "Brooklyn, NY",
    "date": "2026-02-25"
  },
  {
    "name": "Pegassi, Cole Knight, Boy Sanders",
    "venue": "99 Scott",
    "location": "Brooklyn, NY",
    "date": "2026-02-25"
  },
  {
    "name": "Lil Texas",
    "venue": "SILO Brooklyn",
    "location": "Brooklyn, NY",
    "date": "2026-02-25"
  },
  {
    "name": "yetep, KLAXX, juuku, I See Colors",
    "venue": "Racket New York",
    "location": "New York, NY",
    "date": "2026-02-25"
  },
  {
    "name": "Sunsquabi, Manic Focus",
    "venue": "Brooklyn Bowl",
    "location": "Brooklyn, NY",
    "date": "2026-02-25"
  },
  {
    "name": "DR. GABBA, nextdimensional, Switch Angel, Soo Intoit",
    "venue": "Elsewhere",
    "location": "Brooklyn, NY",
    "date": "2026-02-25"
  },
  {
    "name": "Cheeky Bugger Tour: Taiki Nulight, Rohaan",
    "venue": "Bowery Ballroom",
    "location": "New York, NY",
    "date": "2026-02-25"
  },
  {
    "name": "BARELY ALIVE, TYNAN, RiddimNYC",
    "venue": "Webster Hall",
    "location": "New York, NY",
    "date": "2026-02-25"
  },
  {
    "name": "Oppidan",
    "venue": "99 Scott",
    "location": "Brooklyn, NY",
    "date": "2026-02-25"
  },
  {
    "name": "Jeff Mills, Ken Ishii",
    "venue": "Knockdown Center",
    "location": "New York, NY",
    "date": "2026-02-25"
  },
  {
    "name": "\u00d8TTA, Jonah Almost, Zlata, JSMN",
    "venue": "Elsewhere",
    "location": "Brooklyn, NY",
    "date": "2026-02-25"
  },
  {
    "name": "Labyrinth New York debut: Da Capo, Enoo Napa, Nick Castle",
    "venue": "The Chocolate Factory Brooklyn",
    "location": "Brooklyn, NY",
    "date": "2026-02-25"
  },
  {
    "name": "Tom Enzy, Eran Hersh, MAAHEZ, DEROZA",
    "venue": "Superior Ingredients (Main Room)",
    "location": "Brooklyn, NY",
    "date": "2026-02-25"
  },
  {
    "name": "Jody Wisternoff, Wassu",
    "venue": "SILO Brooklyn",
    "location": "Brooklyn, NY",
    "date": "2026-02-25"
  },
  {
    "name": "Andhim",
    "venue": "UNVEILED",
    "location": "Brooklyn, NY",
    "date": "2026-02-25"
  },
  {
    "name": "Lucas & Steve",
    "venue": "Nebula",
    "location": "New York, NY",
    "date": "2026-02-25"
  },
  {
    "name": "Joezi, Darmon, Mish, chandi",
    "venue": "Superior Ingredients (Rooftop)",
    "location": "Brooklyn, NY",
    "date": "2026-03-01"
  },
  {
    "name": "Loco Carnaval Sundays: Oscar G, Lohrasp Kansara, Ladell, Valent\u00edn",
    "venue": "Somewhere Nowhere",
    "location": "New York, NY",
    "date": "2026-03-01"
  },
  {
    "name": "Sundays in the Atrium: Danilo Plessow (MCDE), Shawn Dub",
    "venue": "Public Records",
    "location": "Brooklyn, NY",
    "date": "2026-03-01"
  },
  {
    "name": "Will Automagic, Eli Escobar",
    "venue": "Rumi",
    "location": "New York, NY",
    "date": "2026-03-01"
  },
  {
    "name": "Nelson Paradise Roman",
    "venue": "Refuge",
    "location": "Brooklyn, NY",
    "date": "2026-03-01"
  },
  {
    "name": "Sunday Skate Club: Miss Alicia, DJ Houseplants",
    "venue": "Xanadu Roller Arts",
    "location": "Brooklyn, NY",
    "date": "2026-03-01"
  },
  {
    "name": "M.e.a.t. Brooklyn Afters",
    "venue": "The Meadows Brooklyn",
    "location": "Brooklyn, NY",
    "date": "2026-03-01"
  },
  {
    "name": "Victor Calderone",
    "venue": "Refuge",
    "location": "Brooklyn, NY",
    "date": "2026-03-01"
  },
  {
    "name": "Steen",
    "venue": "SILO Brooklyn",
    "location": "Brooklyn, NY",
    "date": "2026-02-25"
  },
  {
    "name": "Pictureplane, Suzy Sheer, ros3yy",
    "venue": "Sultan Room",
    "location": "Brooklyn, NY",
    "date": "2026-02-25"
  },
  {
    "name": "Gasolina: DJ Ultra Violet",
    "venue": "House of Yes",
    "location": "Brooklyn, NY",
    "date": "2026-02-25"
  },
  {
    "name": "Accessory Records Showcase: Rose Kourts, Miles Mercer b2b Simic, Second Contact",
    "venue": "Signal Brooklyn",
    "location": "Brooklyn, NY",
    "date": "2026-02-25"
  },
  {
    "name": "bambinodj, CZ Wang, Emma DJ b2b Via App, Khotin, Toxe",
    "venue": "Nowadays",
    "location": "New York, NY",
    "date": "2026-02-25"
  },
  {
    "name": "BRUX",
    "venue": "Elsewhere",
    "location": "Brooklyn, NY",
    "date": "2026-02-25"
  },
  {
    "name": "Tour de PR: x3butterfly, Petal Supply, Callie Reiff, Raquel Michel",
    "venue": "Public Records",
    "location": "Brooklyn, NY",
    "date": "2026-02-25"
  },
  {
    "name": "DJ Pauly D",
    "venue": "Marquee",
    "location": "New York, NY",
    "date": "2026-02-25"
  },
  {
    "name": "Roddy Lima",
    "venue": "SILO Brooklyn",
    "location": "Brooklyn, NY",
    "date": "2026-02-25"
  },
  {
    "name": "The Dark Night of The Soul Tour: Kaivon",
    "venue": "Bowery Ballroom",
    "location": "New York, NY",
    "date": "2026-02-25"
  },
  {
    "name": "Mindchatter, Aka Vinnie",
    "venue": "Knockdown Center",
    "location": "New York, NY",
    "date": "2026-02-25"
  },
  {
    "name": "Teksupport x Prophecy: Prospa, Josh Baker",
    "venue": "Brooklyn Storehouse",
    "location": "Brooklyn, NY",
    "date": "2026-02-25"
  },
  {
    "name": "Hernan Cattaneo",
    "venue": "The Chocolate Factory Brooklyn",
    "location": "Brooklyn, NY",
    "date": "2026-02-25"
  },
  {
    "name": "Chris Dave, Rich Medina",
    "venue": "Blue Note Jazz Club",
    "location": "New York, NY",
    "date": "2026-02-25"
  },
  {
    "name": "Indira Paganotto",
    "venue": "Knockdown Center",
    "location": "New York, NY",
    "date": "2026-02-25"
  },
  {
    "name": "Jessica Audiffred",
    "venue": "Brooklyn Steel",
    "location": "Brooklyn, NY",
    "date": "2026-02-25"
  },
  {
    "name": "CHYL",
    "venue": "Racket New York",
    "location": "New York, NY",
    "date": "2026-02-25"
  },
  {
    "name": "Bob Sinclar",
    "venue": "Marquee",
    "location": "New York, NY",
    "date": "2026-02-25"
  },
  {
    "name": "mind enterprises",
    "venue": "Elsewhere Hall",
    "location": "Brooklyn, NY",
    "date": "2026-02-25"
  },
  {
    "name": "Kaivon, PORTYL, KC",
    "venue": "Bowery Ballroom",
    "location": "New York, NY",
    "date": "2026-02-25"
  },
  {
    "name": "Jkyl & Hyde",
    "venue": "SILO Brooklyn",
    "location": "Brooklyn, NY",
    "date": "2026-02-25"
  },
  {
    "name": "Teksupport: Carl Cox, Nicole Moudaber, Ilario Alicante, Viot",
    "venue": "Brooklyn Storehouse",
    "location": "Brooklyn, NY",
    "date": "2026-02-25"
  },
  {
    "name": "FKA twigs, Tokischa",
    "venue": "Madison Square Garden",
    "location": "New York, NY",
    "date": "2026-02-25"
  },
  {
    "name": "Sabo, Unders",
    "venue": "House of Yes",
    "location": "Brooklyn, NY",
    "date": "2026-02-25"
  },
  {
    "name": "OMNOM",
    "venue": "99 Scott",
    "location": "Brooklyn, NY",
    "date": "2026-02-25"
  },
  {
    "name": "Mont Rouge, Auguste, Koti\u0113r, Friend Of Honor, Miss Hazard",
    "venue": "Superior Ingredients (Rooftop)",
    "location": "Brooklyn, NY",
    "date": "2026-02-25"
  },
  {
    "name": "Time Lapse: Darren Styles, RayRay",
    "venue": "Eden NYC",
    "location": "New York, NY",
    "date": "2026-02-25"
  },
  {
    "name": "Emanuel Satie, Sean Doron, Amy Jor",
    "venue": "Superior Ingredients (Rooftop)",
    "location": "Brooklyn, NY",
    "date": "2026-02-25"
  },
  {
    "name": "Sundays in the Atrium: DJ Sprinkles, Frank & Tony",
    "venue": "Public Records",
    "location": "Brooklyn, NY",
    "date": "2026-02-25"
  },
  {
    "name": "Loco Carnaval Sundays: Simone Vitullo, Watson, Saxxdoc, SHNKR",
    "venue": "Somewhere Nowhere",
    "location": "New York, NY",
    "date": "2026-02-25"
  },
  {
    "name": "Jellybean Benitez",
    "venue": "Refuge",
    "location": "Brooklyn, NY",
    "date": "2026-02-25"
  },
  {
    "name": "Maayan Nidam",
    "venue": "Moondog HiFi",
    "location": "Brooklyn, NY",
    "date": "2026-02-25"
  },
  {
    "name": "Sense Invites: Elle Dee, Mod21, 1NTT, Epfnia",
    "venue": "telos.haus",
    "location": "Brooklyn, NY",
    "date": "2026-02-25"
  },
  {
    "name": "Joris Delacroix",
    "venue": "Elsewhere Hall",
    "location": "Brooklyn, NY",
    "date": "2026-02-25"
  },
  {
    "name": "Collective Memory: DJ DEADNAME b2b Eva Loveless, Yumi",
    "venue": "Signal Brooklyn",
    "location": "Brooklyn, NY",
    "date": "2026-02-25"
  },
  {
    "name": "Refuge Thursday",
    "venue": "Refuge",
    "location": "Brooklyn, NY",
    "date": "2026-02-25"
  },
  {
    "name": "R3HAB",
    "venue": "Marquee",
    "location": "New York, NY",
    "date": "2026-02-25"
  },
  {
    "name": "PRADA2000, Flash Gea, Firebunny, Remniqe",
    "venue": "SILO Brooklyn",
    "location": "Brooklyn, NY",
    "date": "2026-02-25"
  },
  {
    "name": "oskar med k",
    "venue": "Webster Hall",
    "location": "New York, NY",
    "date": "2026-02-25"
  },
  {
    "name": "Pan-Pot, ONYVAA",
    "venue": "Knockdown Center",
    "location": "New York, NY",
    "date": "2026-02-25"
  },
  {
    "name": "Adam Ten",
    "venue": "Industry City",
    "location": "Brooklyn, NY",
    "date": "2026-02-25"
  },
  {
    "name": "1 Hotel Brooklyn Bridge",
    "venue": "1 Hotel Brooklyn Bridge",
    "location": "Brooklyn, NY",
    "date": "2026-02-25"
  },
  {
    "name": "Agape Presents: David L\u00f6hlein, Michelle Kay, Junkfile, AKR",
    "venue": "The Chocolate Factory Brooklyn",
    "location": "Brooklyn, NY",
    "date": "2026-02-25"
  },
  {
    "name": "Fideles",
    "venue": "Somewhere Nowhere",
    "location": "New York, NY",
    "date": "2026-02-25"
  },
  {
    "name": "BOUND Blackout: Lolsnake, Elle Dee, Katie Rex, Miss Twink USA, Makadsi, Sterling Juan Diaz",
    "venue": "BASEMENT NY",
    "location": "New York, NY",
    "date": "2026-02-25"
  },
  {
    "name": "Birds of Mind",
    "venue": "UNVEILED",
    "location": "Brooklyn, NY",
    "date": "2026-02-25"
  },
  {
    "name": "Basstripper, Sam Collins",
    "venue": "Elsewhere",
    "location": "Brooklyn, NY",
    "date": "2026-02-25"
  },
  {
    "name": "ReSolute x CHAOS: Fumiya Tanaka",
    "venue": "H0L0",
    "location": "New York, NY",
    "date": "2026-02-25"
  },
  {
    "name": "Last Heroes, Years Of War",
    "venue": "Racket New York",
    "location": "New York, NY",
    "date": "2026-02-25"
  },
  {
    "name": "Friction Presents - Synergy: Friction, Yetti, Samisosa",
    "venue": "Car Park",
    "location": "Brooklyn, NY",
    "date": "2026-02-25"
  },
  {
    "name": "Alix Perez",
    "venue": "SILO Brooklyn",
    "location": "Brooklyn, NY",
    "date": "2026-02-25"
  },
  {
    "name": "Horse Meat Disco, Ryan Farr",
    "venue": "Knockdown Center",
    "location": "New York, NY",
    "date": "2026-02-25"
  },
  {
    "name": "Bradley Zero, Louise Chen, Tornado Wallace, Alex McCracken, Cosmo",
    "venue": "Public Records",
    "location": "Brooklyn, NY",
    "date": "2026-02-25"
  },
  {
    "name": "Swimming Paul",
    "venue": "Marquee",
    "location": "New York, NY",
    "date": "2026-02-25"
  },
  {
    "name": "Alt\u00e6r 6 Year Anniversary: Beste Hira, Yant, Auspex, Ketia, Kim Anh, Will Jack [!",
    "venue": "BASEMENT NY",
    "location": "New York, NY",
    "date": "2026-02-25"
  },
  {
    "name": "Selina Labara",
    "venue": "Somewhere Nowhere",
    "location": "New York, NY",
    "date": "2026-02-25"
  },
  {
    "name": "Ferreck Dawn, Cassimm, Pavel Petrov, Ms. Unicorn, Naiman",
    "venue": "Superior Ingredients (Rooftop)",
    "location": "Brooklyn, NY",
    "date": "2026-02-25"
  },
  {
    "name": "Sunday Selectors",
    "venue": "Refuge",
    "location": "Brooklyn, NY",
    "date": "2026-02-25"
  },
  {
    "name": "Hannah Account, Cades, Alien D, J. Albert, DJ Purple",
    "venue": "Jupiter Disco",
    "location": "Brooklyn, NY",
    "date": "2026-02-25"
  },
  {
    "name": "Atune - Deep Listening",
    "venue": "Moondog HiFi",
    "location": "Brooklyn, NY",
    "date": "2026-03-03"
  }
]